my_library/__init__.py
my_ala_library-0.1.0.dist-info/METADATA
my_ala_library-0.1.0.dist-info/WHEEL
my_ala_library-0.1.0.dist-info/top_level.txt
my_ala_library-0.1.0.dist-info/RECORD
