Metadata-Version: 2.4
Name: my-ala-library
Version: 0.1.0
Summary: My first Python library
Author-email: Alaa <alaa123@gmail.com>
License: MIT
Requires-Python: >=3.7
